{
  "updated": "2026-02-14T18:17:00.140Z",
  "prices": [
    {
      "id": "bitcoin",
      "name": "Bitcoin",
      "symbol": "BTC",
      "price": 69715,
      "change_24h": 1.07957,
      "change_7d": 0.9234343777697612,
      "change_30d": -27.796865917299552,
      "market_cap": 1394377160889,
      "volume_24h": 39908093803,
      "high_24h": 70434,
      "low_24h": 68713,
      "image": "https://coin-images.coingecko.com/coins/images/1/large/bitcoin.png?1696501400"
    },
    {
      "id": "ethereum",
      "name": "Ethereum",
      "symbol": "ETH",
      "price": 2080.78,
      "change_24h": 1.26827,
      "change_7d": 1.5138855360057764,
      "change_30d": -36.971765595110654,
      "market_cap": 251268775260,
      "volume_24h": 16409526399,
      "high_24h": 2100.05,
      "low_24h": 2042.64,
      "image": "https://coin-images.coingecko.com/coins/images/279/large/ethereum.png?1696501628"
    },
    {
      "id": "ripple",
      "name": "XRP",
      "symbol": "XRP",
      "price": 1.48,
      "change_24h": 4.68364,
      "change_7d": 3.7725101551659486,
      "change_30d": -29.167084332606724,
      "market_cap": 89882039153,
      "volume_24h": 2182166980,
      "high_24h": 1.48,
      "low_24h": 1.4,
      "image": "https://coin-images.coingecko.com/coins/images/44/large/xrp-symbol-white-128.png?1696501442"
    },
    {
      "id": "solana",
      "name": "Solana",
      "symbol": "SOL",
      "price": 88.02,
      "change_24h": 4.14402,
      "change_7d": 1.2427928605152214,
      "change_30d": -38.437997889914314,
      "market_cap": 50007279185,
      "volume_24h": 3154805164,
      "high_24h": 88.22,
      "low_24h": 84.22,
      "image": "https://coin-images.coingecko.com/coins/images/4128/large/solana.png?1718769756"
    },
    {
      "id": "dogecoin",
      "name": "Dogecoin",
      "symbol": "DOGE",
      "price": 0.105918,
      "change_24h": 10.29361,
      "change_7d": 8.405150042896882,
      "change_30d": -24.984740673327813,
      "market_cap": 17864973540,
      "volume_24h": 1097588395,
      "high_24h": 0.105884,
      "low_24h": 0.096004,
      "image": "https://coin-images.coingecko.com/coins/images/5/large/dogecoin.png?1696501409"
    },
    {
      "id": "cardano",
      "name": "Cardano",
      "symbol": "ADA",
      "price": 0.290047,
      "change_24h": 6.84496,
      "change_7d": 6.1902747562649445,
      "change_30d": -27.008647583283263,
      "market_cap": 10675344842,
      "volume_24h": 390151556,
      "high_24h": 0.291835,
      "low_24h": 0.271465,
      "image": "https://coin-images.coingecko.com/coins/images/975/large/cardano.png?1696502090"
    }
  ],
  "global": {
    "total_market_cap": 2467964414671.461,
    "total_volume": 92707116252.29843,
    "btc_dominance": 56.48899351452018,
    "eth_dominance": 10.178536918752824,
    "active_cryptos": 18923,
    "markets": 1466,
    "market_cap_change_24h": 1.3845016774355865
  },
  "trending": [
    {
      "id": "pi-network",
      "name": "Pi Network",
      "symbol": "PI",
      "market_cap_rank": 53,
      "thumb": "https://coin-images.coingecko.com/coins/images/54342/standard/pi_network.jpg?1739347576",
      "price_btc": 0.0000024501349856919347,
      "score": 0
    },
    {
      "id": "bitcoin",
      "name": "Bitcoin",
      "symbol": "BTC",
      "market_cap_rank": 1,
      "thumb": "https://coin-images.coingecko.com/coins/images/1/standard/bitcoin.png?1696501400",
      "price_btc": 1,
      "score": 1
    },
    {
      "id": "pudgy-penguins",
      "name": "Pudgy Penguins",
      "symbol": "PENGU",
      "market_cap_rank": 102,
      "thumb": "https://coin-images.coingecko.com/coins/images/52622/standard/PUDGY_PENGUINS_PENGU_PFP.png?1733809110",
      "price_btc": 1.0928565018092424e-7,
      "score": 2
    },
    {
      "id": "pippin",
      "name": "pippin",
      "symbol": "PIPPIN",
      "market_cap_rank": 86,
      "thumb": "https://coin-images.coingecko.com/coins/images/51589/standard/pippin_logo.png?1731570163",
      "price_btc": 0.000010121560008932966,
      "score": 3
    },
    {
      "id": "virtual-protocol",
      "name": "Virtuals Protocol",
      "symbol": "VIRTUAL",
      "market_cap_rank": 107,
      "thumb": "https://coin-images.coingecko.com/coins/images/34057/standard/LOGOMARK.png?1708356054",
      "price_btc": 0.000009792483618312074,
      "score": 4
    },
    {
      "id": "pepe",
      "name": "Pepe",
      "symbol": "PEPE",
      "market_cap_rank": 42,
      "thumb": "https://coin-images.coingecko.com/coins/images/29850/standard/pepe-token.jpeg?1696528776",
      "price_btc": 6.476608199712242e-11,
      "score": 5
    },
    {
      "id": "solana",
      "name": "Solana",
      "symbol": "SOL",
      "market_cap_rank": 7,
      "thumb": "https://coin-images.coingecko.com/coins/images/4128/standard/solana.png?1718769756",
      "price_btc": 0.0012627187446950904,
      "score": 6
    }
  ],
  "stablecoins": [
    {
      "name": "Tether",
      "symbol": "USDT",
      "market_cap": 183758066398,
      "price": 0.999645
    },
    {
      "name": "USDC",
      "symbol": "USDC",
      "market_cap": 73550577649,
      "price": 0.999851
    },
    {
      "name": "Dai",
      "symbol": "DAI",
      "market_cap": 4143315486,
      "price": 0.999627
    }
  ]
}