{
  "updated": "2026-02-12T01:02:30.746Z",
  "prices": [
    {
      "id": "bitcoin",
      "name": "Bitcoin",
      "symbol": "BTC",
      "price": 67475,
      "change_24h": -2.51375,
      "change_7d": -7.597719975498203,
      "change_30d": -25.96113152492037,
      "market_cap": 1348338111850,
      "volume_24h": 55020026416,
      "high_24h": 69215,
      "low_24h": 65932,
      "image": "https://coin-images.coingecko.com/coins/images/1/large/bitcoin.png?1696501400"
    },
    {
      "id": "ethereum",
      "name": "Ethereum",
      "symbol": "ETH",
      "price": 1961.58,
      "change_24h": -3.20165,
      "change_7d": -8.48001783515989,
      "change_30d": -36.54570386841283,
      "market_cap": 236497451997,
      "volume_24h": 24127967089,
      "high_24h": 2029.19,
      "low_24h": 1911.96,
      "image": "https://coin-images.coingecko.com/coins/images/279/large/ethereum.png?1696501628"
    },
    {
      "id": "ripple",
      "name": "XRP",
      "symbol": "XRP",
      "price": 1.38,
      "change_24h": -2.31595,
      "change_7d": -8.925371551092448,
      "change_30d": -32.86587268911514,
      "market_cap": 83895811036,
      "volume_24h": 3375962066,
      "high_24h": 1.42,
      "low_24h": 1.35,
      "image": "https://coin-images.coingecko.com/coins/images/44/large/xrp-symbol-white-128.png?1696501442"
    },
    {
      "id": "solana",
      "name": "Solana",
      "symbol": "SOL",
      "price": 80.01,
      "change_24h": -4.15731,
      "change_7d": -13.096240366176637,
      "change_30d": -42.46977441477039,
      "market_cap": 45415047544,
      "volume_24h": 3958354377,
      "high_24h": 84.2,
      "low_24h": 78.35,
      "image": "https://coin-images.coingecko.com/coins/images/4128/large/solana.png?1718769756"
    },
    {
      "id": "dogecoin",
      "name": "Dogecoin",
      "symbol": "DOGE",
      "price": 0.091566,
      "change_24h": -1.46469,
      "change_7d": -11.863432699074826,
      "change_30d": -32.937848990394095,
      "market_cap": 15442625822,
      "volume_24h": 1093485396,
      "high_24h": 0.093482,
      "low_24h": 0.088365,
      "image": "https://coin-images.coingecko.com/coins/images/5/large/dogecoin.png?1696501409"
    },
    {
      "id": "cardano",
      "name": "Cardano",
      "symbol": "ADA",
      "price": 0.257691,
      "change_24h": -1.91446,
      "change_7d": -10.08610239929851,
      "change_30d": -33.21178477562392,
      "market_cap": 9481838197,
      "volume_24h": 408847361,
      "high_24h": 0.264369,
      "low_24h": 0.251403,
      "image": "https://coin-images.coingecko.com/coins/images/975/large/cardano.png?1696502090"
    }
  ],
  "global": {
    "total_market_cap": 2373698467376.14,
    "total_volume": 130058216401.09581,
    "btc_dominance": 56.8000310154392,
    "eth_dominance": 9.95663577160547,
    "active_cryptos": 18939,
    "markets": 1464,
    "market_cap_change_24h": -1.9167911818096601
  },
  "trending": [
    {
      "id": "berachain-bera",
      "name": "Berachain",
      "symbol": "BERA",
      "market_cap_rank": 192,
      "thumb": "https://coin-images.coingecko.com/coins/images/25235/standard/BERA.png?1738822008",
      "price_btc": 0.000012468145081326098,
      "score": 0
    },
    {
      "id": "uniswap",
      "name": "Uniswap",
      "symbol": "UNI",
      "market_cap_rank": 38,
      "thumb": "https://coin-images.coingecko.com/coins/images/12504/standard/uniswap-logo.png?1720676669",
      "price_btc": 0.00005058727835293254,
      "score": 1
    },
    {
      "id": "pudgy-penguins",
      "name": "Pudgy Penguins",
      "symbol": "PENGU",
      "market_cap_rank": 114,
      "thumb": "https://coin-images.coingecko.com/coins/images/52622/standard/PUDGY_PENGUINS_PENGU_PFP.png?1733809110",
      "price_btc": 9.044315589397936e-8,
      "score": 2
    },
    {
      "id": "bitcoin",
      "name": "Bitcoin",
      "symbol": "BTC",
      "market_cap_rank": 1,
      "thumb": "https://coin-images.coingecko.com/coins/images/1/standard/bitcoin.png?1696501400",
      "price_btc": 1,
      "score": 3
    },
    {
      "id": "solana",
      "name": "Solana",
      "symbol": "SOL",
      "market_cap_rank": 7,
      "thumb": "https://coin-images.coingecko.com/coins/images/4128/standard/solana.png?1718769756",
      "price_btc": 0.0011850207871922948,
      "score": 4
    },
    {
      "id": "layerzero",
      "name": "LayerZero",
      "symbol": "ZRO",
      "market_cap_rank": 103,
      "thumb": "https://coin-images.coingecko.com/coins/images/28206/standard/ftxG9_TJ_400x400.jpeg?1696527208",
      "price_btc": 0.000032395924730546156,
      "score": 5
    },
    {
      "id": "linea",
      "name": "Linea",
      "symbol": "LINEA",
      "market_cap_rank": 310,
      "thumb": "https://coin-images.coingecko.com/coins/images/68507/standard/linea-logo.jpeg?1756025484",
      "price_btc": 6.082688041549967e-8,
      "score": 6
    }
  ],
  "stablecoins": [
    {
      "name": "Tether",
      "symbol": "USDT",
      "market_cap": 183934836037,
      "price": 0.999492
    },
    {
      "name": "USDC",
      "symbol": "USDC",
      "market_cap": 73326938791,
      "price": 0.999935
    },
    {
      "name": "Dai",
      "symbol": "DAI",
      "market_cap": 4184976531,
      "price": 0.999883
    }
  ]
}