{
  "updated": "2026-02-14T18:20:01.153Z",
  "source": "Twelve Data",
  "indices": [
    {
      "symbol": "DAX",
      "name": "DAX (Francfort)",
      "country": "DE",
      "price": 47.014999,
      "open": 46.9,
      "high": 47.19,
      "low": 46.826,
      "prev_close": 46.9,
      "change": 0.11499786,
      "change_pct": 0.245198,
      "volume": 68400,
      "exchange": "NASDAQ",
      "datetime": "2026-02-13"
    }
  ],
  "forex": [
    {
      "symbol": "EUR/GBP",
      "name": "EUR/GBP",
      "rate": 0.86801,
      "change_pct": -0.20579444,
      "datetime": "2026-02-14"
    },
    {
      "symbol": "EUR/CHF",
      "name": "EUR/CHF",
      "rate": 0.91126,
      "change_pct": -0.046068796,
      "datetime": "2026-02-14"
    }
  ],
  "summary": {
    "total_indices": 1,
    "total_forex": 2,
    "market_open": false
  }
}