{
  "updated": "2026-05-04T19:27:32.508Z",
  "source": "Twelve Data",
  "indices": [
    {
      "symbol": "DAX",
      "name": "DAX (Francfort)",
      "country": "DE",
      "price": 44.32,
      "open": 44.83,
      "high": 44.885,
      "low": 44.26,
      "prev_close": 45.152,
      "change": -0.83200043,
      "change_pct": -1.84267,
      "volume": 700,
      "exchange": "NASDAQ",
      "datetime": "2026-05-04"
    }
  ],
  "forex": [
    {
      "symbol": "EUR/GBP",
      "name": "EUR/GBP",
      "rate": 0.86416,
      "change_pct": 0.083387381,
      "datetime": "2026-05-04"
    },
    {
      "symbol": "EUR/CHF",
      "name": "EUR/CHF",
      "rate": 0.91649,
      "change_pct": 0.038203768,
      "datetime": "2026-05-04"
    }
  ],
  "summary": {
    "total_indices": 1,
    "total_forex": 2,
    "market_open": false
  }
}