{
  "updated": "2026-02-19T01:06:23.699Z",
  "source": "Twelve Data",
  "indices": [
    {
      "symbol": "DAX",
      "name": "DAX (Francfort)",
      "country": "DE",
      "price": 47.2125,
      "open": 47.14,
      "high": 47.5059,
      "low": 47.105,
      "prev_close": 47.115,
      "change": 0.097499847,
      "change_pct": 0.20694013,
      "volume": 39201,
      "exchange": "NASDAQ",
      "datetime": "2026-02-18"
    }
  ],
  "forex": [
    {
      "symbol": "EUR/GBP",
      "name": "EUR/GBP",
      "rate": 0.87374,
      "change_pct": 0.073302027,
      "datetime": "2026-02-19"
    },
    {
      "symbol": "EUR/CHF",
      "name": "EUR/CHF",
      "rate": 0.911,
      "change_pct": 0.021958718,
      "datetime": "2026-02-19"
    }
  ],
  "summary": {
    "total_indices": 1,
    "total_forex": 2,
    "market_open": false
  }
}