{
  "updated": "2026-03-25T07:00:37.722Z",
  "source": "FRED (Federal Reserve Economic Data)",
  "indicators": [
    {
      "id": "CPIAUCSL",
      "label": "Inflation (CPI)",
      "value": 327.46,
      "date": "2026-02-01",
      "unit": "index",
      "change": 2.66,
      "change_type": "yoy",
      "previous": {
        "value": 326.588,
        "date": "2026-01-01"
      }
    },
    {
      "id": "DFF",
      "label": "Taux directeur (Fed Funds)",
      "value": 3.64,
      "date": "2026-03-23",
      "unit": "%",
      "change": 0,
      "change_type": "abs",
      "previous": {
        "value": 3.64,
        "date": "2026-03-22"
      }
    },
    {
      "id": "GDP",
      "label": "PIB (trimestriel)",
      "value": 31442.483,
      "date": "2025-10-01",
      "unit": "Mrd $",
      "change": 344.46,
      "change_type": "abs",
      "previous": {
        "value": 31098.027,
        "date": "2025-07-01"
      }
    },
    {
      "id": "UNRATE",
      "label": "Chômage",
      "value": 4.4,
      "date": "2026-02-01",
      "unit": "%",
      "change": 0.1,
      "change_type": "abs",
      "previous": {
        "value": 4.3,
        "date": "2026-01-01"
      }
    },
    {
      "id": "DTWEXBGS",
      "label": "Dollar Index (broad)",
      "value": 120.2757,
      "date": "2026-03-20",
      "unit": "index",
      "change": 0.1,
      "change_type": "abs",
      "previous": {
        "value": 120.1802,
        "date": "2026-03-19"
      }
    },
    {
      "id": "M2SL",
      "label": "Masse monétaire M2",
      "value": 22667.3,
      "date": "2026-02-01",
      "unit": "Mrd $",
      "change": 198.2,
      "change_type": "abs",
      "previous": {
        "value": 22469.1,
        "date": "2026-01-01"
      }
    }
  ]
}