{
  "updated": "2026-02-25T01:06:16.311Z",
  "quotes": [
    {
      "symbol": "SPY",
      "name": "S&P 500",
      "price": 687.35,
      "change": 0.7269,
      "change_abs": 4.96,
      "high": 688.35,
      "low": 680,
      "open": 681.9,
      "prev_close": 682.39,
      "is_proxy": true
    },
    {
      "symbol": "QQQ",
      "name": "Nasdaq 100",
      "price": 607.87,
      "change": 1.0741,
      "change_abs": 6.46,
      "high": 608.99,
      "low": 599.73,
      "open": 602.4,
      "prev_close": 601.41,
      "is_proxy": true
    },
    {
      "symbol": "DIA",
      "name": "Dow Jones",
      "price": 491.79,
      "change": 0.7746,
      "change_abs": 3.78,
      "high": 492.85,
      "low": 487.45,
      "open": 488.39,
      "prev_close": 488.01,
      "is_proxy": true
    },
    {
      "symbol": "GLD",
      "name": "Or (ETF)",
      "price": 474.61,
      "change": -1.3859,
      "change_abs": -6.67,
      "high": 475.44,
      "low": 469.55,
      "open": 470.085,
      "prev_close": 481.28,
      "is_proxy": true
    },
    {
      "symbol": "USO",
      "name": "Pétrole (ETF)",
      "price": 80.76,
      "change": -0.1731,
      "change_abs": -0.14,
      "high": 81.22,
      "low": 79.8,
      "open": 81.19,
      "prev_close": 80.9,
      "is_proxy": true
    },
    {
      "symbol": "NVDA",
      "name": "Nvidia",
      "price": 192.85,
      "change": 0.6787,
      "change_abs": 1.3,
      "high": 193.77,
      "low": 187.4,
      "open": 191.49,
      "prev_close": 191.55,
      "is_proxy": false
    },
    {
      "symbol": "AAPL",
      "name": "Apple",
      "price": 272.14,
      "change": 2.2391,
      "change_abs": 5.96,
      "high": 274.89,
      "low": 267.71,
      "open": 267.86,
      "prev_close": 266.18,
      "is_proxy": false
    },
    {
      "symbol": "MSFT",
      "name": "Microsoft",
      "price": 389,
      "change": 1.1782,
      "change_abs": 4.53,
      "high": 389.36,
      "low": 381.71,
      "open": 384.14,
      "prev_close": 384.47,
      "is_proxy": false
    },
    {
      "symbol": "GOOGL",
      "name": "Alphabet",
      "price": 310.9,
      "change": -0.1894,
      "change_abs": -0.59,
      "high": 312.27,
      "low": 305.93,
      "open": 310.515,
      "prev_close": 311.49,
      "is_proxy": false
    },
    {
      "symbol": "TSLA",
      "name": "Tesla",
      "price": 409.38,
      "change": 2.3885,
      "change_abs": 9.55,
      "high": 410.82,
      "low": 397.64,
      "open": 399.5,
      "prev_close": 399.83,
      "is_proxy": false
    }
  ],
  "economicCalendar": [],
  "summary": {
    "total_symbols": 10,
    "market_open": false,
    "calendar_events": 0
  }
}